automation_fw_setup/__init__.py
automation_fw_setup/__main__.py
automation_fw_setup/ask_target_platform.py
automation_fw_setup/ask_test_framework.py
automation_fw_setup/check_for_updates.py
automation_fw_setup/check_installations.py
automation_fw_setup/clone_repository.py
automation_fw_setup/create_project_folder.py
automation_fw_setup/create_virtual_env.py
automation_fw_setup/requirements_install.py
automation_fw_setup-1.0.1.dist-info/LICENSE
automation_fw_setup-1.0.1.dist-info/METADATA
automation_fw_setup-1.0.1.dist-info/WHEEL
automation_fw_setup-1.0.1.dist-info/entry_points.txt
automation_fw_setup-1.0.1.dist-info/top_level.txt
automation_fw_setup-1.0.1.dist-info/RECORD
